{"title":"Beyonce - Lemonade ALBUM 2016 MP3 320 Kbps Sammy","uid":14414082,"size":110678284,"categoryP":"audio","categoryS":"other","magnet":"?xt=urn:btih:03c7e4fb3ef76d2e86455a32312d6fcd401d7d6e&amp;dn=Beyonce+-+Lemonade+ALBUM+2016+MP3+320+Kbps+Sammy&amp;tr=udp%3A%2F%2Ftracker.leechers-paradise.org%3A6969&amp;tr=udp%3A%2F%2Fzer0day.ch%3A1337&amp;tr=udp%3A%2F%2Fopen.demonii.com%3A1337&amp;tr=udp%3A%2F%2Ftracker.coppersurfer.tk%3A6969&amp;tr=udp%3A%2F%2Fexodus.desync.com%3A6969","seeders":6,"leechers":0,"uploader":"LTBS","files":20,"time":1461474278,"description":"Beyonce - Lemonade ALBUM 2016 MP3 320 Kbps Sammy","torrent":{"xt":"urn:btih:03c7e4fb3ef76d2e86455a32312d6fcd401d7d6e","amp;dn":"Beyonce+-+Lemonade+ALBUM+2016+MP3+320+Kbps+Sammy","amp;tr":["udp%3A%2F%2Ftracker.leechers-paradise.org%3A6969","udp%3A%2F%2Fzer0day.ch%3A1337","udp%3A%2F%2Fopen.demonii.com%3A1337","udp%3A%2F%2Ftracker.coppersurfer.tk%3A6969","udp%3A%2F%2Fexodus.desync.com%3A6969"],"infoHash":"03c7e4fb3ef76d2e86455a32312d6fcd401d7d6e","infoHashBuffer":{"type":"Buffer","data":[3,199,228,251,62,247,109,46,134,69,90,50,49,45,111,205,64,29,125,110]},"announce":[],"urlList":[]}}