{"title":"DevilsFilm - Aubrey Kate, Gio - The Tranny Bunch, Scene 02","uid":11908768,"size":1015711077,"categoryP":"porn","categoryS":"movie_clips","magnet":"?xt=urn:btih:0f51a0286fe47f65ff594d4dbe68bbdf69dc35cf&amp;dn=DevilsFilm+-+Aubrey+Kate%2C+Gio+-+The+Tranny+Bunch%2C+Scene+02&amp;tr=udp%3A%2F%2Ftracker.openbittorrent.com%3A80&amp;tr=udp%3A%2F%2Fopen.demonii.com%3A1337&amp;tr=udp%3A%2F%2Ftracker.coppersurfer.tk%3A6969&amp;tr=udp%3A%2F%2Fexodus.desync.com%3A6969","seeders":7,"leechers":12,"uploader":"HighCode","files":3,"time":1431389641,"description":"DevilsFilm - Aubrey Kate, Gio - The Tranny Bunch, Scene 02 [.mp4]\n\nScreenshots: &lt;a href=&quot;\nhttp://imgclover.com/image/OZR&quot; rel=&quot;nofollow&quot; target=&quot;_NEW&quot;&gt;\nhttp://imgclover.com/image/OZR&lt;/a&gt; &lt;a href=&quot;\nhttp://imgclover.com/image/OZZ&quot; rel=&quot;nofollow&quot; target=&quot;_NEW&quot;&gt;\nhttp://imgclover.com/image/OZZ&lt;/a&gt;","torrent":{"xt":"urn:btih:0f51a0286fe47f65ff594d4dbe68bbdf69dc35cf","amp;dn":"DevilsFilm+-+Aubrey+Kate%2C+Gio+-+The+Tranny+Bunch%2C+Scene+02","amp;tr":["udp%3A%2F%2Ftracker.openbittorrent.com%3A80","udp%3A%2F%2Fopen.demonii.com%3A1337","udp%3A%2F%2Ftracker.coppersurfer.tk%3A6969","udp%3A%2F%2Fexodus.desync.com%3A6969"],"infoHash":"0f51a0286fe47f65ff594d4dbe68bbdf69dc35cf","infoHashBuffer":{"type":"Buffer","data":[15,81,160,40,111,228,127,101,255,89,77,77,190,104,187,223,105,220,53,207]},"announce":[],"urlList":[]}}