{"title":"Awesome Mix of 200 Amateur's With Big Asses Pic Set Homemade","uid":11927260,"size":48494666,"categoryP":"porn","categoryS":"pictures","magnet":"?xt=urn:btih:14ab7e38138769f9bc11900e654db021d373f40f&amp;dn=Awesome+Mix+of+200+Amateur%27s+With+Big+Asses+Pic+Set+Homemade&amp;tr=udp%3A%2F%2Ftracker.openbittorrent.com%3A80&amp;tr=udp%3A%2F%2Fopen.demonii.com%3A1337&amp;tr=udp%3A%2F%2Ftracker.coppersurfer.tk%3A6969&amp;tr=udp%3A%2F%2Fexodus.desync.com%3A6969","seeders":7,"leechers":0,"uploader":"Ctrlme","files":201,"time":1431732360,"description":"Awesome Mix of 200 Amateur's With Big Asses Pic Set Homemade (Teens, Wives - Lots of chubby/plumper/BBW) all ive gotta say is...DAMN! Look at DAT ASS!!!!\n\nScreenshot(s):    &lt;a href=&quot;\nhttp://imgsay.com/viewshare.php?file=741810img.jpg&quot; rel=&quot;nofollow&quot; target=&quot;_NEW&quot;&gt;\nhttp://imgsay.com/viewshare.php?file=741810img.jpg&lt;/a&gt; &lt;a href=&quot;\nhttp://imgsay.com/viewshare.php?file=494550jav.jpg&quot; rel=&quot;nofollow&quot; target=&quot;_NEW&quot;&gt;\nhttp://imgsay.com/viewshare.php?file=494550jav.jpg&lt;/a&gt; &lt;a href=&quot;\nhttp://imgsay.com/viewshare.php?file=494551jav2.jpg&quot; rel=&quot;nofollow&quot; target=&quot;_NEW&quot;&gt;\nhttp://imgsay.com/viewshare.php?file=494551jav2.jpg&lt;/a&gt;","torrent":{"xt":"urn:btih:14ab7e38138769f9bc11900e654db021d373f40f","amp;dn":"Awesome+Mix+of+200+Amateur%27s+With+Big+Asses+Pic+Set+Homemade","amp;tr":["udp%3A%2F%2Ftracker.openbittorrent.com%3A80","udp%3A%2F%2Fopen.demonii.com%3A1337","udp%3A%2F%2Ftracker.coppersurfer.tk%3A6969","udp%3A%2F%2Fexodus.desync.com%3A6969"],"infoHash":"14ab7e38138769f9bc11900e654db021d373f40f","infoHashBuffer":{"type":"Buffer","data":[20,171,126,56,19,135,105,249,188,17,144,14,101,77,176,33,211,115,244,15]},"announce":[],"urlList":[]}}