{"title":"World.Of.Goo.Full.PC.ENG.","uid":4470684,"size":65231060,"categoryP":"games","categoryS":"pc","magnet":"?xt=urn:btih:201fd3ff7bec241a6900e38ffb7f8c9e112eeeb7&amp;dn=World.Of.Goo.Full.PC.ENG.&amp;tr=udp%3A%2F%2Ftracker.openbittorrent.com%3A80&amp;tr=udp%3A%2F%2Fopen.demonii.com%3A1337&amp;tr=udp%3A%2F%2Ftracker.coppersurfer.tk%3A6969&amp;tr=udp%3A%2F%2Fexodus.desync.com%3A6969","seeders":7,"leechers":0,"uploader":"Lazy1234","files":1,"time":1225118972,"description":"World of Goo is a physics based puzzle / construction game. The millions of Goo Balls who live in the beautiful World of Goo don't know that they are in a game, or that they are extremely delicious.","torrent":{"xt":"urn:btih:201fd3ff7bec241a6900e38ffb7f8c9e112eeeb7","amp;dn":"World.Of.Goo.Full.PC.ENG.","amp;tr":["udp%3A%2F%2Ftracker.openbittorrent.com%3A80","udp%3A%2F%2Fopen.demonii.com%3A1337","udp%3A%2F%2Ftracker.coppersurfer.tk%3A6969","udp%3A%2F%2Fexodus.desync.com%3A6969"],"infoHash":"201fd3ff7bec241a6900e38ffb7f8c9e112eeeb7","infoHashBuffer":{"type":"Buffer","data":[32,31,211,255,123,236,36,26,105,0,227,143,251,127,140,158,17,46,238,183]},"announce":[],"urlList":[]}}