{"title":"[MyDirtyHobby] Angel-Desert - Sperm story Kaffee mit Sperma (29.","uid":13398525,"size":109083266,"categoryP":"porn","categoryS":"movie_clips","magnet":"?xt=urn:btih:324b5f8fb29ef087afee757a2283cb7751f4dd04&amp;dn=%5BMyDirtyHobby%5D+Angel-Desert+-+Sperm+story+Kaffee+mit+Sperma+%2829.&amp;tr=udp%3A%2F%2Ftracker.leechers-paradise.org%3A6969&amp;tr=udp%3A%2F%2Fzer0day.ch%3A1337&amp;tr=udp%3A%2F%2Fopen.demonii.com%3A1337&amp;tr=udp%3A%2F%2Ftracker.coppersurfer.tk%3A6969&amp;tr=udp%3A%2F%2Fexodus.desync.com%3A6969","seeders":7,"leechers":1,"uploader":"KayWily","files":1,"time":1454380849,"description":"[MyDirtyHobby] Angel-Desert - Sperm story Kaffee mit Sperma (29.05.2015)\r\n\r\n \nhttp://porn-harbor.com/image/J4S","torrent":{"xt":"urn:btih:324b5f8fb29ef087afee757a2283cb7751f4dd04","amp;dn":"%5BMyDirtyHobby%5D+Angel-Desert+-+Sperm+story+Kaffee+mit+Sperma+%2829.","amp;tr":["udp%3A%2F%2Ftracker.leechers-paradise.org%3A6969","udp%3A%2F%2Fzer0day.ch%3A1337","udp%3A%2F%2Fopen.demonii.com%3A1337","udp%3A%2F%2Ftracker.coppersurfer.tk%3A6969","udp%3A%2F%2Fexodus.desync.com%3A6969"],"infoHash":"324b5f8fb29ef087afee757a2283cb7751f4dd04","infoHashBuffer":{"type":"Buffer","data":[50,75,95,143,178,158,240,135,175,238,117,122,34,131,203,119,81,244,221,4]},"announce":[],"urlList":[]}}