{"title":"The Mechanic[2011]DvDrip[Eng]-FXG","uid":6311415,"size":734176683,"categoryP":"video","categoryS":"movies","magnet":"?xt=urn:btih:373bc9779a6f53f7496cafe185b8cebfe5d87b4d&amp;dn=The+Mechanic%5B2011%5DDvDrip%5BEng%5D-FXG&amp;tr=udp%3A%2F%2Ftracker.openbittorrent.com%3A80&amp;tr=udp%3A%2F%2Fopen.demonii.com%3A1337&amp;tr=udp%3A%2F%2Ftracker.coppersurfer.tk%3A6969&amp;tr=udp%3A%2F%2Fexodus.desync.com%3A6969","seeders":7,"leechers":3,"uploader":"FXG_team","files":4,"time":1302552813,"description":"TiTLE.........[ The Mechanic\nYEAR..........[ 2011\nGENRE.........[ Action | Crime | Thriller        \nRUNTiME.......[ 1:32:44\niMDB RATE.....[ 6.5/10   (13,584 votes) \nFXG RATE......[ 7.0/10   (2 votes)\niMDB URL......[ http://www.imdb.com/title/tt0472399/\n\nAUDiO.........[ MP3 48000Hz 128 kb/s CBR (2 chnls)\nLANGUAGE......[ English       \nViDEO.........[ 918 kbps XviD 23.976 FPS\nRESOLUTiON....[ 2.500 (5:2)\nDAR...........[ 1.875 (15:8)\nQUALiTY FRAME.[ 0.207\nSUBS..........[ English\nSiZE..........[ 700 MB\nSOURCE........[ NTSC DVD\n\nRiP...........[ #524\nRELEASE DATE..[ 11/04/2011\n\n\n\nPLOT SUMMARY\n\n\n\nFollows an elite hit man as he teaches his trade to an apprentice who has a connection to one of his previous victims.    \n\n\n\n\nExtra Notes :\n\nMake sure its a real genuine release from me @\n\nYou can also find me through","torrent":{"xt":"urn:btih:373bc9779a6f53f7496cafe185b8cebfe5d87b4d","amp;dn":"The+Mechanic%5B2011%5DDvDrip%5BEng%5D-FXG","amp;tr":["udp%3A%2F%2Ftracker.openbittorrent.com%3A80","udp%3A%2F%2Fopen.demonii.com%3A1337","udp%3A%2F%2Ftracker.coppersurfer.tk%3A6969","udp%3A%2F%2Fexodus.desync.com%3A6969"],"infoHash":"373bc9779a6f53f7496cafe185b8cebfe5d87b4d","infoHashBuffer":{"type":"Buffer","data":[55,59,201,119,154,111,83,247,73,108,175,225,133,184,206,191,229,216,123,77]},"announce":[],"urlList":[]}}