{"title":"[Tightandteen]Private - Lexi Belle - Blonde Lexie Belle as the","uid":14174953,"size":711252321,"categoryP":"porn","categoryS":"movie_clips","magnet":"?xt=urn:btih:55a2c7af472e0982480a0bef49ba38fd16ef87f9&amp;dn=+%5BTightandteen%5DPrivate+-+Lexi+Belle+-+Blonde+Lexie+Belle+as+the+&amp;tr=udp%3A%2F%2Ftracker.leechers-paradise.org%3A6969&amp;tr=udp%3A%2F%2Fzer0day.ch%3A1337&amp;tr=udp%3A%2F%2Fopen.demonii.com%3A1337&amp;tr=udp%3A%2F%2Ftracker.coppersurfer.tk%3A6969&amp;tr=udp%3A%2F%2Fexodus.desync.com%3A6969","seeders":7,"leechers":1,"uploader":"LucasCar","files":1,"time":1459798304,"description":"[Tightandteen]Private - Lexi Belle - Blonde Lexie Belle as the Tightest Teen Pussy[.mp4] \r\n \nhttp://naughtyimage.com/img-5702a4e62489a.html\r\n \nhttp://naughtyimage.com/img-5702a4f1d09c1.html\r\n\r\n\r\n\r\n* * * For more stuff please visit * * *                                 \nhttps://thepiratebay.se/user/LucasCar/","torrent":{"xt":"urn:btih:55a2c7af472e0982480a0bef49ba38fd16ef87f9","amp;dn":"+%5BTightandteen%5DPrivate+-+Lexi+Belle+-+Blonde+Lexie+Belle+as+the+","amp;tr":["udp%3A%2F%2Ftracker.leechers-paradise.org%3A6969","udp%3A%2F%2Fzer0day.ch%3A1337","udp%3A%2F%2Fopen.demonii.com%3A1337","udp%3A%2F%2Ftracker.coppersurfer.tk%3A6969","udp%3A%2F%2Fexodus.desync.com%3A6969"],"infoHash":"55a2c7af472e0982480a0bef49ba38fd16ef87f9","infoHashBuffer":{"type":"Buffer","data":[85,162,199,175,71,46,9,130,72,10,11,239,73,186,56,253,22,239,135,249]},"announce":[],"urlList":[]}}