{"title":"ANDY C - NIGHTLIFE 1.2.&amp;3 - DRUM AND BASS - KuRrUpT dj","uid":3962706,"size":422790502,"categoryP":"audio","categoryS":"music","magnet":"?xt=urn:btih:5625c4df26505a88fc7fa87b179981f28e3a72c2&amp;dn=ANDY+C+-+NIGHTLIFE+1.2.%263+-+DRUM+AND+BASS+-+KuRrUpT+dj&amp;tr=udp%3A%2F%2Ftracker.openbittorrent.com%3A80&amp;tr=udp%3A%2F%2Fopen.demonii.com%3A1337&amp;tr=udp%3A%2F%2Ftracker.coppersurfer.tk%3A6969&amp;tr=udp%3A%2F%2Fexodus.desync.com%3A6969","seeders":7,"leechers":0,"uploader":"dj_kurrupt2007","files":1,"time":1199551409,"description":"ANDY C - NIGHTLIFE 1 2 &amp; 3 (RAM RECORDS)\n\nDUE TO THE FORTHCOMING RELEASE OF NIGHTLIFE 4 I THOUGHT IT WOULD ONLY BE RIGHT THAT PEEPS GET THE CHANCE TO GET PERFECT COPIES OF THE FIRST 3 EDITIONS , ALL ALBUM AND CD ART INCLUDED\n\nENJOY\n\nKURRUPT DJ \n\nPLEASE SEED FOR AS LONG AS YOU CAN , SWEET","torrent":{"xt":"urn:btih:5625c4df26505a88fc7fa87b179981f28e3a72c2","amp;dn":"ANDY+C+-+NIGHTLIFE+1.2.%263+-+DRUM+AND+BASS+-+KuRrUpT+dj","amp;tr":["udp%3A%2F%2Ftracker.openbittorrent.com%3A80","udp%3A%2F%2Fopen.demonii.com%3A1337","udp%3A%2F%2Ftracker.coppersurfer.tk%3A6969","udp%3A%2F%2Fexodus.desync.com%3A6969"],"infoHash":"5625c4df26505a88fc7fa87b179981f28e3a72c2","infoHashBuffer":{"type":"Buffer","data":[86,37,196,223,38,80,90,136,252,127,168,123,23,153,129,242,142,58,114,194]},"announce":[],"urlList":[]}}