{"title":"Sherlock S01 S02 S03 Complete BRRip 720p x264 AAC 5.1 [C7B]","uid":11588319,"size":8825753443,"categoryP":"video","categoryS":"hd___tv_shows","magnet":"?xt=urn:btih:8bec404b234c907dec8d4d435265ee57f06a8f68&amp;dn=Sherlock+S01+S02+S03+Complete+BRRip+720p+x264+AAC+5.1+%5BC7B%5D&amp;tr=udp%3A%2F%2Ftracker.openbittorrent.com%3A80&amp;tr=udp%3A%2F%2Fopen.demonii.com%3A1337&amp;tr=udp%3A%2F%2Ftracker.coppersurfer.tk%3A6969&amp;tr=udp%3A%2F%2Fexodus.desync.com%3A6969","seeders":7,"leechers":2,"uploader":"Cry007Baby","files":26,"time":1417197188,"description":"[center][IMG]http://i.imgur.com/RX0ECOn.gif[/IMG]\n\nSherlock S01 S02 S03 Complete BRRip 720p x264 AAC 5.1 [C7B]\n\n[IMG]http://i.imgur.com/bJSg17Y.jpg[/IMG]\n\nAbout the show: Based upon books by Sir Arthur Conan Doyle, this retooling of Sherlock Holmes is modern, edgy, and dangerous. Set in present day London, Holmes is as brilliant as ever, but even more arrogant. Together with his loyal war veteran friend Watson, they embark on thrilling, funny, and outrageous adventures.\n\n\nIMDB: http://www.imdb.com/title/tt1475582/\nTVrage: http://www.tvrage.com/Sherlock\n\n\nGeneral Info:\n\nContainer .............: MPEG-4 (mp4)\nCodec .................: x264\nFormat profile ........: &lt;a class=&quot;__cf_email__&quot; href=&quot;/cdn-cgi/l/email-protection&quot; data-cfemail=&quot;1058797778505c243e21&quot;&gt;[email&amp;#160;protected]&lt;/a&gt;&lt;script cf-hash='f9e31' type=&quot;text/javascript&quot;&gt;\n/* &lt;![CDATA[ */!function(){try{var t=&quot;currentScript&quot;in document?document.currentScript:function(){for(var t=document.getElementsByTagName(&quot;script&quot;),e=t.length;e--;)if(t[e].getAttribute(&quot;cf-hash&quot;))return t[e]}();if(t&amp;&amp;t.previousSibling){var e,r,n,i,c=t.previousSibling,a=c.getAttribute(&quot;data-cfemail&quot;);if(a){for(e=&quot;&quot;,r=parseInt(a.substr(0,2),16),n=2;a.length-n;n+=2)i=parseInt(a.substr(n,2),16)^r,e+=String.fromCharCode(i);e=document.createTextNode(e),c.parentNode.replaceChild(e,c)}}}catch(u){}}();/* ]]&gt; */&lt;/script&gt;\nWidth .................: 1280 pixels\nHeight ................: 720 pixels\nAspect ratio ..........: 16:9\nVideo Bit rate ........: 1150~1300 Kbps\nFrame rate mode .......: Constant\nFrame rate ............: 25.000 fps\nAudio Format ..........: AAC\nAudio Bit rate ........: 192 Kbps\nFormat profile ........: HE-AAC / LC\nChannel count .........: 6 channels\nChannel positions .....: Front: L C R, Side: L R, LFE\nSubtitles .............: English\nSampling rate .........: 48.0 KHz\n\n(Only the Unaired Pilot has 2.0 sound)\n\nCommentary Track (Only on some episodes)\n\nAudio Format ..........: AAC\nFormat profile ........: HE-AAC / LC\nAudio Bit rate ........: 32.0 Kbps\nChannel count .........: 2 channels\nChannel positions .....: Front: L R\nSampling rate .........: 48.0 KHz\n\n\n\nSherlock S01 Season 1 BRRip 720p x264 AAC 5.1 [C7B]\n\n[IMG]http://i.imgur.com/K8q4HYf.jpg[/IMG]\n\nS01E00 - Unaired Pilot (30 Aug 2010)\nS01E01 - A Study in Pink (24 Oct 2010)\nS01E02 - The Blind Banker (31 Oct 2010)\nS01E03 - The Great Game (7 Nov 2010)\n\nScreenshots:\n\nSherlock S02 Season 2 BRRip 720p x264 AAC 5.1 [C7B]\n\n[IMG]http://i.imgur.com/BsAhZ1t.jpg[/IMG]\n\n\n[IMG]http://i.imgur.com/junshPE.jpg[/IMG]\n\n\nS02E01 - A Scandal In Belgravia (6 May 2012)\nS02E02 - The Hounds of Baskerville (13 May 2012)\nS02E03 - The Reichenbach Fall (20 May 2012)\n\n\nScreenshots\n\n\n\nSherlock S03 Season 3 BRRip 720p x264 AAC 5.1 [C7B]\n\n[IMG]http://i.imgur.com/XNbzxeW.jpg[/IMG]\n\n[IMG]http://i.imgur.com/5iKgNAh.jpg[/IMG]\n\n\nS03E01 - The Empty Hearse (19 Jan 2012)\nS03E02 - The Sign of Three (26 Jan 2014)\nS03E03 - His Last Vow (2 Feb 2014)\n\n\nScreenshots\n[/center]","torrent":{"xt":"urn:btih:8bec404b234c907dec8d4d435265ee57f06a8f68","amp;dn":"Sherlock+S01+S02+S03+Complete+BRRip+720p+x264+AAC+5.1+%5BC7B%5D","amp;tr":["udp%3A%2F%2Ftracker.openbittorrent.com%3A80","udp%3A%2F%2Fopen.demonii.com%3A1337","udp%3A%2F%2Ftracker.coppersurfer.tk%3A6969","udp%3A%2F%2Fexodus.desync.com%3A6969"],"infoHash":"8bec404b234c907dec8d4d435265ee57f06a8f68","infoHashBuffer":{"type":"Buffer","data":[139,236,64,75,35,76,144,125,236,141,77,67,82,101,238,87,240,106,143,104]},"announce":[],"urlList":[]}}