{"title":"Ch4 Dispatches 2014 Rice How Safe Is Our Food 720p x264 AAC HDTV","uid":11397167,"size":545942931,"categoryP":"video","categoryS":"hd___tv_shows","magnet":"?xt=urn:btih:8ec993e56421230a6bc89c30e7104b3eb82861b7&amp;dn=Ch4+Dispatches+2014+Rice+How+Safe+Is+Our+Food+720p+x264+AAC+HDTV&amp;tr=udp%3A%2F%2Ftracker.openbittorrent.com%3A80&amp;tr=udp%3A%2F%2Fopen.demonii.com%3A1337&amp;tr=udp%3A%2F%2Ftracker.coppersurfer.tk%3A6969&amp;tr=udp%3A%2F%2Fexodus.desync.com%3A6969","seeders":7,"leechers":2,"uploader":"MVGroup","files":-1,"time":1415378905,"description":"Rice: How Safe is Our Food?\n\nScience Documentary hosted by Morland Sanders, published by Channel 4 broadcasted as part of CH4 Dispatches series in 2014 - English narration\n\n\nInformation\n------------------------------\n\nRice: How Safe Is Our Food?\nWe're eating more rice than ever before. It's in our ready meals, our breakfast cereals and in the food we feed our children. But some leading scientists and experts are warning that some types of commonly consumed rice contain a worrying level of naturally occurring arsenic. \nYou can find very low levels of arsenic in most food and water but researchers are concerned that arsenic can reach much higher levels in rice. \nWhile there are strict limits for the arsenic level permitted in water, there are currently no maximum levels for our food and some scientists are now speaking out as they are concerned about the effects of long-term exposure. \nAs more evidence emerges about the harm high levels of arsenic might cause, particularly to children, new maximum levels are being proposed by the government and the European Union. \nMorland Sanders investigates these new proposals and reveals the results of tests on some of our most popular rice products.\n\nScreenshots\n------------------------------\nclick on the links below to get full-size images &lt;a href=&quot;\nhttp://image.bayimg.com/a2ece4411cc82b0deedea48e54e8505e461bf983.jpg&quot; rel=&quot;nofollow&quot; target=&quot;_NEW&quot;&gt;\nhttp://image.bayimg.com/a2ece4411cc82b0deedea48e54e8505e461bf983.jpg&lt;/a&gt; &lt;a href=&quot;\nhttp://image.bayimg.com/a04da17baf6b90842741a89a32622cc9d852b532.jpg&quot; rel=&quot;nofollow&quot; target=&quot;_NEW&quot;&gt;\nhttp://image.bayimg.com/a04da17baf6b90842741a89a32622cc9d852b532.jpg&lt;/a&gt; &lt;a href=&quot;\nhttp://image.bayimg.com/c4b3e4f9047ab74bcbdda375f00f860350b392c3.jpg&quot; rel=&quot;nofollow&quot; target=&quot;_NEW&quot;&gt;\nhttp://image.bayimg.com/c4b3e4f9047ab74bcbdda375f00f860350b392c3.jpg&lt;/a&gt; &lt;a href=&quot;\nhttp://image.bayimg.com/534656f60eb3ee0a2362d9c8ec2e311dc11b2d9c.jpg&quot; rel=&quot;nofollow&quot; target=&quot;_NEW&quot;&gt;\nhttp://image.bayimg.com/534656f60eb3ee0a2362d9c8ec2e311dc11b2d9c.jpg&lt;/a&gt; &lt;a href=&quot;\nhttp://image.bayimg.com/0209b2c051fa5ada6a231fa1885dd33101a8b3c3.jpg&quot; rel=&quot;nofollow&quot; target=&quot;_NEW&quot;&gt;\nhttp://image.bayimg.com/0209b2c051fa5ada6a231fa1885dd33101a8b3c3.jpg&lt;/a&gt; &lt;a href=&quot;\nhttp://image.bayimg.com/0ca4eb85eedc1da468989979fd7c04bd22255730.jpg&quot; rel=&quot;nofollow&quot; target=&quot;_NEW&quot;&gt;\nhttp://image.bayimg.com/0ca4eb85eedc1da468989979fd7c04bd22255730.jpg&lt;/a&gt; &lt;a href=&quot;\nhttp://image.bayimg.com/703c7189ff0c0ba5f01bad174d631b0c20e245cf.jpg&quot; rel=&quot;nofollow&quot; target=&quot;_NEW&quot;&gt;\nhttp://image.bayimg.com/703c7189ff0c0ba5f01bad174d631b0c20e245cf.jpg&lt;/a&gt; &lt;a href=&quot;\nhttp://image.bayimg.com/b05ecbd88a4a6e0bbe1cbbf8855c97af6f07455c.jpg&quot; rel=&quot;nofollow&quot; target=&quot;_NEW&quot;&gt;\nhttp://image.bayimg.com/b05ecbd88a4a6e0bbe1cbbf8855c97af6f07455c.jpg&lt;/a&gt; &lt;a href=&quot;\nhttp://image.bayimg.com/b4a93879139eb8b278b5eaa068fb8c39e82fdf96.jpg&quot; rel=&quot;nofollow&quot; target=&quot;_NEW&quot;&gt;\nhttp://image.bayimg.com/b4a93879139eb8b278b5eaa068fb8c39e82fdf96.jpg&lt;/a&gt; &lt;a href=&quot;\nhttp://image.bayimg.com/dac1eacc17f7f62691d60a1b62d73a643aa6045c.jpg&quot; rel=&quot;nofollow&quot; target=&quot;_NEW&quot;&gt;\nhttp://image.bayimg.com/dac1eacc17f7f62691d60a1b62d73a643aa6045c.jpg&lt;/a&gt; &lt;a href=&quot;\nhttp://image.bayimg.com/db22fac7c9c26d24290e978fed3529b412eec647.jpg&quot; rel=&quot;nofollow&quot; target=&quot;_NEW&quot;&gt;\nhttp://image.bayimg.com/db22fac7c9c26d24290e978fed3529b412eec647.jpg&lt;/a&gt; &lt;a href=&quot;\nhttp://image.bayimg.com/61764326a525ebc0086ba5fecf0c66c8f679e010.jpg&quot; rel=&quot;nofollow&quot; target=&quot;_NEW&quot;&gt;\nhttp://image.bayimg.com/61764326a525ebc0086ba5fecf0c66c8f679e010.jpg&lt;/a&gt; \n\nTechnical Specs\n------------------------------\n\n\n * Video Codec: x264 CABAC &lt;a class=&quot;__cf_email__&quot; href=&quot;/cdn-cgi/l/email-protection&quot; data-cfemail=&quot;1159787679515d253f20&quot;&gt;[email&amp;#160;protected]&lt;/a&gt;&lt;script cf-hash='f9e31' type=&quot;text/javascript&quot;&gt;\n/* &lt;![CDATA[ */!function(){try{var t=&quot;currentScript&quot;in document?document.currentScript:function(){for(var t=document.getElementsByTagName(&quot;script&quot;),e=t.length;e--;)if(t[e].getAttribute(&quot;cf-hash&quot;))return t[e]}();if(t&amp;&amp;t.previousSibling){var e,r,n,i,c=t.previousSibling,a=c.getAttribute(&quot;data-cfemail&quot;);if(a){for(e=&quot;&quot;,r=parseInt(a.substr(0,2),16),n=2;a.length-n;n+=2)i=parseInt(a.substr(n,2),16)^r,e+=String.fromCharCode(i);e=document.createTextNode(e),c.parentNode.replaceChild(e,c)}}}catch(u){}}();/* ]]&gt; */&lt;/script&gt;\n * Video Bitrate: 2680 Kbps\n * Video Aspect Ratio: 1.778 (16:9)\n * Video Resolution: 1280 x 720\n * Audio Codec: AAC LC\n * Audio English\n * Audio Bitrate: 160 kb/s VBR 48 KHz\n * Audio Channels: Stereo 2\n * Run-Time: 28mins\n * Framerate: 25 FPS\n * Number of Parts: 1\n * Container Mp4\n * Part Size: 520 MB\n * Source: HDTV\n * Encoded by: Harry65\n\n1)  Further Information &lt;a href=&quot;\nhttp://www.channel4.com/programmes/dispatches/articles/all/rice-how-safe-is-it&quot; rel=&quot;nofollow&quot; target=&quot;_NEW&quot;&gt;\nhttp://www.channel4.com/programmes/dispatches/articles/all/rice-how-safe-is-it&lt;/a&gt;\n\n2)  Related Documentaries &lt;a href=&quot;\nhttp://docuwiki.net/?title=Our%20Food&quot; rel=&quot;nofollow&quot; target=&quot;_NEW&quot;&gt;\nhttp://docuwiki.net/?title=Our%20Food&lt;/a&gt; &lt;a href=&quot;\nhttp://docuwiki.net/?title=The%20Food%20We%20Eat&quot; rel=&quot;nofollow&quot; target=&quot;_NEW&quot;&gt;\nhttp://docuwiki.net/?title=The%20Food%20We%20Eat&lt;/a&gt; &lt;a href=&quot;\nhttp://docuwiki.net/?title=The%20Truth%20about%20Food&quot; rel=&quot;nofollow&quot; target=&quot;_NEW&quot;&gt;\nhttp://docuwiki.net/?title=The%20Truth%20about%20Food&lt;/a&gt; &lt;a href=&quot;\nhttp://docuwiki.net/?title=The%20Truth%20about%20Low%20Fat%20Food&quot; rel=&quot;nofollow&quot; target=&quot;_NEW&quot;&gt;\nhttp://docuwiki.net/?title=The%20Truth%20about%20Low%20Fat%20Food&lt;/a&gt; &lt;a href=&quot;\nhttp://docuwiki.net/?title=Food%3A%20Whats%20Really%20In%20Your%20Trolley%3F&quot; rel=&quot;nofollow&quot; target=&quot;_NEW&quot;&gt;\nhttp://docuwiki.net/?title=Food%3A%20Whats%20Really%20In%20Your%20Trolley%3F&lt;/a&gt; &lt;a href=&quot;\nhttp://docuwiki.net/?title=The%20Truth%20About%20Taste&quot; rel=&quot;nofollow&quot; target=&quot;_NEW&quot;&gt;\nhttp://docuwiki.net/?title=The%20Truth%20About%20Taste&lt;/a&gt;","torrent":{"xt":"urn:btih:8ec993e56421230a6bc89c30e7104b3eb82861b7","amp;dn":"Ch4+Dispatches+2014+Rice+How+Safe+Is+Our+Food+720p+x264+AAC+HDTV","amp;tr":["udp%3A%2F%2Ftracker.openbittorrent.com%3A80","udp%3A%2F%2Fopen.demonii.com%3A1337","udp%3A%2F%2Ftracker.coppersurfer.tk%3A6969","udp%3A%2F%2Fexodus.desync.com%3A6969"],"infoHash":"8ec993e56421230a6bc89c30e7104b3eb82861b7","infoHashBuffer":{"type":"Buffer","data":[142,201,147,229,100,33,35,10,107,200,156,48,231,16,75,62,184,40,97,183]},"announce":[],"urlList":[]}}