{"title":"Metal.Hurlant.Chronicles.S01E03.BDRip.XviD-RedBlade.avi","uid":7884233,"size":182334928,"categoryP":"video","categoryS":"tv_shows","magnet":"?xt=urn:btih:8ef16dbfd4f12714da6ae124d7e252f85713fc9f&amp;dn=Metal.Hurlant.Chronicles.S01E03.BDRip.XviD-RedBlade.avi&amp;tr=udp%3A%2F%2Ftracker.openbittorrent.com%3A80&amp;tr=udp%3A%2F%2Fopen.demonii.com%3A1337&amp;tr=udp%3A%2F%2Ftracker.coppersurfer.tk%3A6969&amp;tr=udp%3A%2F%2Fexodus.desync.com%3A6969","seeders":8,"leechers":1,"uploader":"helder1965","files":-1,"time":1354574436,"description":"Enjoy and seed it, buddies!\n@helder1965","torrent":{"xt":"urn:btih:8ef16dbfd4f12714da6ae124d7e252f85713fc9f","amp;dn":"Metal.Hurlant.Chronicles.S01E03.BDRip.XviD-RedBlade.avi","amp;tr":["udp%3A%2F%2Ftracker.openbittorrent.com%3A80","udp%3A%2F%2Fopen.demonii.com%3A1337","udp%3A%2F%2Ftracker.coppersurfer.tk%3A6969","udp%3A%2F%2Fexodus.desync.com%3A6969"],"infoHash":"8ef16dbfd4f12714da6ae124d7e252f85713fc9f","infoHashBuffer":{"type":"Buffer","data":[142,241,109,191,212,241,39,20,218,106,225,36,215,226,82,248,87,19,252,159]},"announce":[],"urlList":[]}}