{"title":"The League S01E04 HDTV XviD-SYS [eztv]","uid":5171505,"size":367263744,"categoryP":"video","categoryS":"tv_shows","magnet":"?xt=urn:btih:998a1a7475dd35092104c4984824589829b299fd&amp;dn=The+League+S01E04+HDTV+XviD-SYS+%5Beztv%5D&amp;tr=udp%3A%2F%2Ftracker.openbittorrent.com%3A80&amp;tr=udp%3A%2F%2Fopen.demonii.com%3A1337&amp;tr=udp%3A%2F%2Ftracker.coppersurfer.tk%3A6969&amp;tr=udp%3A%2F%2Fexodus.desync.com%3A6969","seeders":7,"leechers":1,"uploader":"eztv","files":1,"time":1258715730,"description":"#EZTV @ EFNet -&gt; To avoid fakes, ALWAYS check that the torrent was added by eztv. &lt;a href=&quot;\nhttp://eztv.it/&quot; rel=&quot;nofollow&quot; target=&quot;_NEW&quot;&gt;\nhttp://eztv.it/&lt;/a&gt;\n\nEpisode: The League S01E04 HDTV XviD-SYS\nScreenshots: &lt;a href=&quot;\nhttp://www.imgden.com/2694/The.League.S01E04.HDTV.XviD-SYS.avi.jpg&quot; rel=&quot;nofollow&quot; target=&quot;_NEW&quot;&gt;\nhttp://www.imgden.com/2694/The.League.S01E04.HDTV.XviD-SYS.avi.jpg&lt;/a&gt;\n\n\nWant to help us out? BitCoin: 1Fw4sRdZYFwULfeE7oQ91GLYKy8j5EcuFW","torrent":{"xt":"urn:btih:998a1a7475dd35092104c4984824589829b299fd","amp;dn":"The+League+S01E04+HDTV+XviD-SYS+%5Beztv%5D","amp;tr":["udp%3A%2F%2Ftracker.openbittorrent.com%3A80","udp%3A%2F%2Fopen.demonii.com%3A1337","udp%3A%2F%2Ftracker.coppersurfer.tk%3A6969","udp%3A%2F%2Fexodus.desync.com%3A6969"],"infoHash":"998a1a7475dd35092104c4984824589829b299fd","infoHashBuffer":{"type":"Buffer","data":[153,138,26,116,117,221,53,9,33,4,196,152,72,36,88,152,41,178,153,253]},"announce":[],"urlList":[]}}