{"title":"Les.Infideles.2012.EXTENDED.720p.BluRay.x264-SEiGHT [PublicHD]","uid":7393513,"size":5863199019,"categoryP":"video","categoryS":"hd___movies","magnet":"?xt=urn:btih:a214b97403de2a60bb3ec3f73449ff7b725e9bce&amp;dn=Les.Infideles.2012.EXTENDED.720p.BluRay.x264-SEiGHT+%5BPublicHD%5D&amp;tr=udp%3A%2F%2Ftracker.openbittorrent.com%3A80&amp;tr=udp%3A%2F%2Fopen.demonii.com%3A1337&amp;tr=udp%3A%2F%2Ftracker.coppersurfer.tk%3A6969&amp;tr=udp%3A%2F%2Fexodus.desync.com%3A6969","seeders":8,"leechers":1,"uploader":"TPBAgri","files":3,"time":1340847725,"description":"PublicHD - High-Definition Bittorrent Community \n    &lt;a href=&quot;\nhttp://publichd.eu/&quot; rel=&quot;nofollow&quot; target=&quot;_NEW&quot;&gt;\nhttp://publichd.eu/&lt;/a&gt;\n\n-----------------------------------------------------\n\nLes.Infideles.2012.EXTENDED.720p.BluRay.x264-SEiGHT [PublicHD]\n &lt;a href=&quot;\nhttp://www.imdb.com/title/tt2087850/&quot; rel=&quot;nofollow&quot; target=&quot;_NEW&quot;&gt;\nhttp://www.imdb.com/title/tt2087850/&lt;/a&gt;\n\nRELEASE DATE....: 27/06/12\nVIDEO...........: 1280x544 @ 4782kbps\nAUDIO...........: FRENCH DTS 1510KBPS\nGENRE...........: Comedie\nRUNTIME.........: 02h05min\nSUBS............: Fr forced\n","torrent":{"xt":"urn:btih:a214b97403de2a60bb3ec3f73449ff7b725e9bce","amp;dn":"Les.Infideles.2012.EXTENDED.720p.BluRay.x264-SEiGHT+%5BPublicHD%5D","amp;tr":["udp%3A%2F%2Ftracker.openbittorrent.com%3A80","udp%3A%2F%2Fopen.demonii.com%3A1337","udp%3A%2F%2Ftracker.coppersurfer.tk%3A6969","udp%3A%2F%2Fexodus.desync.com%3A6969"],"infoHash":"a214b97403de2a60bb3ec3f73449ff7b725e9bce","infoHashBuffer":{"type":"Buffer","data":[162,20,185,116,3,222,42,96,187,62,195,247,52,73,255,123,114,94,155,206]},"announce":[],"urlList":[]}}