{"title":"Hurricane Season (2009) DVDR NL Subs DivXNL-Team","uid":5248528,"size":729893788,"categoryP":"video","categoryS":"movies","magnet":"?xt=urn:btih:a90315ab93820835fc81761f7a488f552c215503&amp;dn=Hurricane+Season+%282009%29+DVDR+NL+Subs+DivXNL-Team&amp;tr=udp%3A%2F%2Ftracker.openbittorrent.com%3A80&amp;tr=udp%3A%2F%2Fopen.demonii.com%3A1337&amp;tr=udp%3A%2F%2Ftracker.coppersurfer.tk%3A6969&amp;tr=udp%3A%2F%2Fexodus.desync.com%3A6969","seeders":7,"leechers":0,"uploader":"DivXNL-Team","files":3,"time":1262244580,"description":"[img]http://yourmainsource.net/wp-content/uploads/2009/12/hurricane-season-movie-poster.jpg[/img]\nHurricane Season (2009)\n\nVerenigde Staten\nDrama\n\ngeregisseerd door Tim Story\nmet Forest Whitaker, Isaiah Washington en Bow Wow\n\nWaargebeurd verhaal over een basketbalteam in de nadagen van orkaan Katrina. Coach Al Collins selecteert een groep jongens van vijf verschillende scholen, die achtergebleven zijn in New Orleans en de overstromingen hebben overleefd. Volledig onverwacht zetten zij een ongekende winstserie neer in de Staats-league.\n\n\n\nHurricane Season (2009) \n\nMovie..............: Hurricane Season (2009) \ngenre..............: Drama\nSource.............: Hurricane Season 2009 DVDRip XviD-DOMiNO\nFormat.............: DivX\nruntime............: 103 min.\nMenu...............: No\nVideo..............: Compressed\nAudio..............: Eng: DD 2.0\nSubtitles..........: Vertaald door Snowii, super job M8 en welcome back!!!\nControle...........: Snowii\nBewerking+Resync...: Snowii\n\n \nCategorie : Beeld \nFormaat : DivX \nBron : Retail\nOndertitels : Nederlands \nGenre: Drama\n  &lt;a href=&quot;\nhttp://www.moviemeter.nl/film/52972&quot; rel=&quot;nofollow&quot; target=&quot;_NEW&quot;&gt;\nhttp://www.moviemeter.nl/film/52972&lt;/a&gt;  &lt;a href=&quot;\nhttp://www.imdb.com/title/tt1172998/&quot; rel=&quot;nofollow&quot; target=&quot;_NEW&quot;&gt;\nhttp://www.imdb.com/title/tt1172998/&lt;/a&gt;\n\n\n[b][color=Orange]DivXNL-Team Means; Hardburned Dutch Subbed[/color][/b]\n\n[url=http://www.divxnl-team.nl/index.php]DivXNL, De NL Films Site[/url]\n\n","torrent":{"xt":"urn:btih:a90315ab93820835fc81761f7a488f552c215503","amp;dn":"Hurricane+Season+%282009%29+DVDR+NL+Subs+DivXNL-Team","amp;tr":["udp%3A%2F%2Ftracker.openbittorrent.com%3A80","udp%3A%2F%2Fopen.demonii.com%3A1337","udp%3A%2F%2Ftracker.coppersurfer.tk%3A6969","udp%3A%2F%2Fexodus.desync.com%3A6969"],"infoHash":"a90315ab93820835fc81761f7a488f552c215503","infoHashBuffer":{"type":"Buffer","data":[169,3,21,171,147,130,8,53,252,129,118,31,122,72,143,85,44,33,85,3]},"announce":[],"urlList":[]}}