{"title":"Teen.Mom.2.S03E03.Things.Come.To.An.End_Tam.avi","uid":7870695,"size":329560850,"categoryP":"video","categoryS":"tv_shows","magnet":"?xt=urn:btih:ae56843f0bc17093ee613eda3a21af1ba6175495&amp;dn=Teen.Mom.2.S03E03.Things.Come.To.An.End_Tam.avi&amp;tr=udp%3A%2F%2Ftracker.openbittorrent.com%3A80&amp;tr=udp%3A%2F%2Fopen.demonii.com%3A1337&amp;tr=udp%3A%2F%2Ftracker.coppersurfer.tk%3A6969&amp;tr=udp%3A%2F%2Fexodus.desync.com%3A6969","seeders":8,"leechers":2,"uploader":"AlbaGuBrath","files":-1,"time":1354196149,"description":"Teen Mom 2 Season 3 Episode 3 - 'Things Come To An End'\n\n\nLeah and Corey finalize their divorce, and Chelsea's dad finds out that Adam is living with her. Jenelle goes against her lawyer's advice, while Kailyn finds a picture of Jo and his girlfriend online.\n\nEnjoy!!\n\nTam&amp;Carla\n\n\n","torrent":{"xt":"urn:btih:ae56843f0bc17093ee613eda3a21af1ba6175495","amp;dn":"Teen.Mom.2.S03E03.Things.Come.To.An.End_Tam.avi","amp;tr":["udp%3A%2F%2Ftracker.openbittorrent.com%3A80","udp%3A%2F%2Fopen.demonii.com%3A1337","udp%3A%2F%2Ftracker.coppersurfer.tk%3A6969","udp%3A%2F%2Fexodus.desync.com%3A6969"],"infoHash":"ae56843f0bc17093ee613eda3a21af1ba6175495","infoHashBuffer":{"type":"Buffer","data":[174,86,132,63,11,193,112,147,238,97,62,218,58,33,175,27,166,23,84,149]},"announce":[],"urlList":[]}}