{"title":"Kama Sutra (ErosExotica)","uid":6622591,"size":675432096,"categoryP":"porn","categoryS":"movies","magnet":"?xt=urn:btih:b37a3373e85a64e7632bbc5f8c1d642d21baa8fa&amp;dn=Kama+Sutra+%28ErosExotica%29&amp;tr=udp%3A%2F%2Ftracker.openbittorrent.com%3A80&amp;tr=udp%3A%2F%2Fopen.demonii.com%3A1337&amp;tr=udp%3A%2F%2Ftracker.coppersurfer.tk%3A6969&amp;tr=udp%3A%2F%2Fexodus.desync.com%3A6969","seeders":7,"leechers":0,"uploader":"inst23","files":-1,"time":1314049558,"description":"Kama Sutra (ErosExotica)\n\nYear: 2008\nCountry: USA\nGenre: Erotic, Educational\nRun Time: 1 hour and 3 minutes\nLanguage: English\nDirector: Pierre Roshan\nStudio: Al!ve AG\nStarring: Sahara Knite, Will Steiger  \n\nScreenlist: &lt;a href=&quot; http://i26.fastpic.ru/big/2011/0822/c5/19614d95879c16b657ca4e03478ff4c5.jpg&quot; rel=&quot;nofollow&quot; target=&quot;_NEW&quot;&gt; http://i26.fastpic.ru/big/2011/0822/c5/19614d95879c16b657ca4e03478ff4c5.jpg&lt;/a&gt;\n\nDescription: Kamasutra is the ancient Indian art of love. Kamasutra is full of tingling eroticism, a wide-ranging selection of sexual technics and postures, but also of wisdom about love and partnership. All this is in artful images with atmospheric music presented, which enchants the senses.\n\n","torrent":{"xt":"urn:btih:b37a3373e85a64e7632bbc5f8c1d642d21baa8fa","amp;dn":"Kama+Sutra+%28ErosExotica%29","amp;tr":["udp%3A%2F%2Ftracker.openbittorrent.com%3A80","udp%3A%2F%2Fopen.demonii.com%3A1337","udp%3A%2F%2Ftracker.coppersurfer.tk%3A6969","udp%3A%2F%2Fexodus.desync.com%3A6969"],"infoHash":"b37a3373e85a64e7632bbc5f8c1d642d21baa8fa","infoHashBuffer":{"type":"Buffer","data":[179,122,51,115,232,90,100,231,99,43,188,95,140,29,100,45,33,186,168,250]},"announce":[],"urlList":[]}}