{"title":"The Strain - The Night Eternal 004 (2014) (digital) (Son of Ultr","uid":11512595,"size":34985961,"categoryP":"other","categoryS":"comics","magnet":"?xt=urn:btih:b3c7220144bdf43c76d282b245a0833562e69692&amp;dn=The+Strain+-+The+Night+Eternal+004+%282014%29+%28digital%29+%28Son+of+Ultr&amp;tr=udp%3A%2F%2Ftracker.openbittorrent.com%3A80&amp;tr=udp%3A%2F%2Fopen.demonii.com%3A1337&amp;tr=udp%3A%2F%2Ftracker.coppersurfer.tk%3A6969&amp;tr=udp%3A%2F%2Fexodus.desync.com%3A6969","seeders":7,"leechers":0,"uploader":"nemesis43","files":1,"time":1416412831,"description":"The Strain - The Night Eternal 004 (2014) (digital) (Son of Ultron-Empire)","torrent":{"xt":"urn:btih:b3c7220144bdf43c76d282b245a0833562e69692","amp;dn":"The+Strain+-+The+Night+Eternal+004+%282014%29+%28digital%29+%28Son+of+Ultr","amp;tr":["udp%3A%2F%2Ftracker.openbittorrent.com%3A80","udp%3A%2F%2Fopen.demonii.com%3A1337","udp%3A%2F%2Ftracker.coppersurfer.tk%3A6969","udp%3A%2F%2Fexodus.desync.com%3A6969"],"infoHash":"b3c7220144bdf43c76d282b245a0833562e69692","infoHashBuffer":{"type":"Buffer","data":[179,199,34,1,68,189,244,60,118,210,130,178,69,160,131,53,98,230,150,146]},"announce":[],"urlList":[]}}