{"title":"Paranormal Activity {2007) BRRip-XviD~Wolftatt2~","uid":6745015,"size":1906622544,"categoryP":"video","categoryS":"hd___movies","magnet":"?xt=urn:btih:b5de4c7ec743891b9342789689e883b229fa9331&amp;dn=Paranormal+Activity+%7B2007%29+BRRip-XviD%7EWolftatt2%7E&amp;tr=udp%3A%2F%2Ftracker.openbittorrent.com%3A80&amp;tr=udp%3A%2F%2Fopen.demonii.com%3A1337&amp;tr=udp%3A%2F%2Ftracker.coppersurfer.tk%3A6969&amp;tr=udp%3A%2F%2Fexodus.desync.com%3A6969","seeders":7,"leechers":0,"uploader":"Applemaggot","files":3,"time":1318654275,"description":"Paranormal Activity {2007)\n\nAfter a young, middle class couple moves into a suburban 'starter' tract house, they become increasingly disturbed by a presence that may or may not be somehow demonic but is certainly most active in the middle of the night. Especially when they sleep. Or try to.\n &lt;a href=&quot;\nhttp://www.imdb.com/title/tt1179904/&quot; rel=&quot;nofollow&quot; target=&quot;_NEW&quot;&gt;\nhttp://www.imdb.com/title/tt1179904/&lt;/a&gt;\n\n\nComplete name                    : Paranormal Activity {2007) BRRip-XviD~Wolftatt2~.avi\nFormat                                 : AVI\nFormat/Info                          : Audio Video Interleave\nFile size                                : 1.78 GiB\nDuration                               : 1h 26mn\nOverall bit rate                      : 2 946 Kbps\n\nThanks for downloading.\n\nPlease Seed!\n\n~Wolftatt2~  ","torrent":{"xt":"urn:btih:b5de4c7ec743891b9342789689e883b229fa9331","amp;dn":"Paranormal+Activity+%7B2007%29+BRRip-XviD%7EWolftatt2%7E","amp;tr":["udp%3A%2F%2Ftracker.openbittorrent.com%3A80","udp%3A%2F%2Fopen.demonii.com%3A1337","udp%3A%2F%2Ftracker.coppersurfer.tk%3A6969","udp%3A%2F%2Fexodus.desync.com%3A6969"],"infoHash":"b5de4c7ec743891b9342789689e883b229fa9331","infoHashBuffer":{"type":"Buffer","data":[181,222,76,126,199,67,137,27,147,66,120,150,137,232,131,178,41,250,147,49]},"announce":[],"urlList":[]}}