{"title":"Infernal Restraints--Pull  Violet Monroe High","uid":15417585,"size":2886071735,"categoryP":"porn","categoryS":"hd___movies","magnet":"?xt=urn:btih:ce5aacc7f2a04f81745e39665a0cf30d13b06fc0&amp;dn=Infernal+Restraints--Pull++Violet+Monroe+High&amp;tr=udp%3A%2F%2Ftracker.leechers-paradise.org%3A6969&amp;tr=udp%3A%2F%2Fzer0day.ch%3A1337&amp;tr=udp%3A%2F%2Fopen.demonii.com%3A1337&amp;tr=udp%3A%2F%2Ftracker.coppersurfer.tk%3A6969&amp;tr=udp%3A%2F%2Fexodus.desync.com%3A6969","seeders":7,"leechers":0,"uploader":"merzedes","files":1,"time":1469600320,"description":"Pull | Violet Monroe\r\n\r\nJuly 22, 2016\r\n\r\n\r\nHigh MP4 only.\r\n\r\n\r\nTied Up Toy Torments Own Tits \r\n \r\nViolet Monroe doesn't know what to do when she finds herself completely immobilized by shackles holding down her arms and legs. She thrashes them around, looking around for someone to help her, panicked at not having control over her body. And now that she's lost mobility O.T. is going to make it much worse for her. Being tormented by someone else is one thing, but when your own body betrays you things get so much scarier.\r\n\r\nO.T. attaches clamps to Violet's nipples and her pussy and then ties all of them to her big toes. This way every time she moves, no matter how little, she will be tugging at the most sensitive parts of her own body. The next step is to make her move. O.T. tickles Violet up and down her body, getting little shrieks of pain mixed in with her uncontrollable laughter. Then he goes to work on her with the Hitachi, the most powerful handheld vibrator in our arsenal, and watches as she tries not to move too much with every wave of pleasure. \r\n\r\nNext he attaches a clamp to Violet's tongue, ties it to her toes, and sets to work caning the bottoms of her feet. This new position adds insult to injury as Violet is humiliated by the ridiculous sounds she makes and the trail of drool steadily leaking from her gaping mouth. Violet is completely powerless and has no choice but to keep pulling at herself, making her pain worse with every moment.\r\n \r\nScreens \nhttp://www.infernalrestraints.com/device/bondage/trailer.php?y=2016&amp;p=07_22vmonroe3&amp;u=InfernalRestraints-Violet-Monroe-Pull\r\n\r\nUploaded by Merzedes and Shallow2\r\n\r\n21 000 Femdom/BDSM/Fetish torrentuploads since 2004, including almost everything from Kink/Intersect.\r\n\r\nJust keep on leaving us nice comments below and we are happy for the next 20k:)\r\n\r\nAlso, a huge thanks to Kink.com for making the videos we all love (and Intersect and all the others too ofcourse). Keep up the awesome work!!!\r\n\r\nAny Questions ?? Read our FAQ!!\r\n \nhttps://yuq.me/users/23/079/W2kwa6hEeP.png\r\n \nhttps://s16.postimg.org/rxyfmji7p/Merzedes_Shallow2_FAQ_The_Pirate_Bay.jpg\r\n\r\nCheers :-)","torrent":{"xt":"urn:btih:ce5aacc7f2a04f81745e39665a0cf30d13b06fc0","amp;dn":"Infernal+Restraints--Pull++Violet+Monroe+High","amp;tr":["udp%3A%2F%2Ftracker.leechers-paradise.org%3A6969","udp%3A%2F%2Fzer0day.ch%3A1337","udp%3A%2F%2Fopen.demonii.com%3A1337","udp%3A%2F%2Ftracker.coppersurfer.tk%3A6969","udp%3A%2F%2Fexodus.desync.com%3A6969"],"infoHash":"ce5aacc7f2a04f81745e39665a0cf30d13b06fc0","infoHashBuffer":{"type":"Buffer","data":[206,90,172,199,242,160,79,129,116,94,57,102,90,12,243,13,19,176,111,192]},"announce":[],"urlList":[]}}