{"title":"Das Sex-Hotel: The Sex Hotel XXX GERMAN (DVDRip)","uid":11811794,"size":1469106176,"categoryP":"porn","categoryS":"movies","magnet":"?xt=urn:btih:da06203a96a08b9bfd4e90e22c8dbdc717f6364f&amp;dn=Das+Sex-Hotel%3A+The+Sex+Hotel+XXX+GERMAN+%28DVDRip%29&amp;tr=udp%3A%2F%2Ftracker.openbittorrent.com%3A80&amp;tr=udp%3A%2F%2Fopen.demonii.com%3A1337&amp;tr=udp%3A%2F%2Ftracker.coppersurfer.tk%3A6969&amp;tr=udp%3A%2F%2Fexodus.desync.com%3A6969","seeders":8,"leechers":8,"uploader":"xuluhulu","files":1,"time":1428849491,"description":"Welcome to SEX HOTEL! A hotel where everything is possible! The SEX HOTEL is a compelling story in the style of a classic, crazy Comedy, full of intrigue and humor - and lots of SEX !!! Both the oversexed staff and the guests are mistaken spin around and finally found in the wildest sex orgies again ...(google translation..)\n\nCOVERS:\n &lt;a href=&quot;\nhttp://imghell.com/viewer.php?file=49567371205329308161.jpg&quot; rel=&quot;nofollow&quot; target=&quot;_NEW&quot;&gt;\nhttp://imghell.com/viewer.php?file=49567371205329308161.jpg&lt;/a&gt;\n &lt;a href=&quot;\nhttp://imghell.com/viewer.php?file=37891632243922270071.jpg&quot; rel=&quot;nofollow&quot; target=&quot;_NEW&quot;&gt;\nhttp://imghell.com/viewer.php?file=37891632243922270071.jpg&lt;/a&gt;\n\n\nTHUMBSNAIL SCREENS:\n &lt;a href=&quot;\nhttp://imghell.com/viewer.php?file=12592040313390467817.jpg&quot; rel=&quot;nofollow&quot; target=&quot;_NEW&quot;&gt;\nhttp://imghell.com/viewer.php?file=12592040313390467817.jpg&lt;/a&gt;\n\n\nCAST:\n\nRonnie    Caroline Andress    Isabel Vibe    Jacob    Nikki Dane    Jade Summers    Jens XP    Mr. Martini    Don LP    Katizi    Monika Henry    Darla DeLovely    Mike Beck    Ã…ke Gustavsson   \n\n\nSEED &amp; ENJOY!!!","torrent":{"xt":"urn:btih:da06203a96a08b9bfd4e90e22c8dbdc717f6364f","amp;dn":"Das+Sex-Hotel%3A+The+Sex+Hotel+XXX+GERMAN+%28DVDRip%29","amp;tr":["udp%3A%2F%2Ftracker.openbittorrent.com%3A80","udp%3A%2F%2Fopen.demonii.com%3A1337","udp%3A%2F%2Ftracker.coppersurfer.tk%3A6969","udp%3A%2F%2Fexodus.desync.com%3A6969"],"infoHash":"da06203a96a08b9bfd4e90e22c8dbdc717f6364f","infoHashBuffer":{"type":"Buffer","data":[218,6,32,58,150,160,139,155,253,78,144,226,44,141,189,199,23,246,54,79]},"announce":[],"urlList":[]}}