{"title":"Harley.and.the.Davidsons.Part.2.XviD-AFG","uid":15776116,"size":293126590,"categoryP":"video","categoryS":"tv_shows","magnet":"?xt=urn:btih:dff2b6227436e6f80875b09a6adbfb864e074794&amp;dn=Harley.and.the.Davidsons.Part.2.XviD-AFG&amp;tr=udp%3A%2F%2Ftracker.leechers-paradise.org%3A6969&amp;tr=udp%3A%2F%2Fzer0day.ch%3A1337&amp;tr=udp%3A%2F%2Fopen.demonii.com%3A1337&amp;tr=udp%3A%2F%2Ftracker.coppersurfer.tk%3A6969&amp;tr=udp%3A%2F%2Fexodus.desync.com%3A6969","seeders":7,"leechers":2,"uploader":"TvTeam","files":7,"time":1473233216,"description":"Torrent from:\r\n~~~~~~~~~~~~ \nhttps://www.torrenting.com\r\n\r\nJoin us and become part of the BIG family! Yarrrrrrrrrrrrrr!!!","torrent":{"xt":"urn:btih:dff2b6227436e6f80875b09a6adbfb864e074794","amp;dn":"Harley.and.the.Davidsons.Part.2.XviD-AFG","amp;tr":["udp%3A%2F%2Ftracker.leechers-paradise.org%3A6969","udp%3A%2F%2Fzer0day.ch%3A1337","udp%3A%2F%2Fopen.demonii.com%3A1337","udp%3A%2F%2Ftracker.coppersurfer.tk%3A6969","udp%3A%2F%2Fexodus.desync.com%3A6969"],"infoHash":"dff2b6227436e6f80875b09a6adbfb864e074794","infoHashBuffer":{"type":"Buffer","data":[223,242,182,34,116,54,230,248,8,117,176,154,106,219,251,134,78,7,71,148]},"announce":[],"urlList":[]}}