{"title":"Outpost 11 [2012] BRRip XViD-ETRG","uid":9207793,"size":737373917,"categoryP":"video","categoryS":"movies","magnet":"?xt=urn:btih:f73ae0610d496418e13d7e0aa4072acdade51f87&amp;dn=Outpost+11+%5B2012%5D+BRRip+XViD-ETRG&amp;tr=udp%3A%2F%2Ftracker.openbittorrent.com%3A80&amp;tr=udp%3A%2F%2Fopen.demonii.com%3A1337&amp;tr=udp%3A%2F%2Ftracker.coppersurfer.tk%3A6969&amp;tr=udp%3A%2F%2Fexodus.desync.com%3A6969","seeders":7,"leechers":3,"uploader":"juggs99","files":5,"time":1384726868,"description":" &lt;a href=&quot;http://www.imdb.com/title/tt2133302/&quot; rel=&quot;nofollow&quot; target=&quot;_NEW&quot;&gt;http://www.imdb.com/title/tt2133302/&lt;/a&gt;\n\nVIDEO :-                                               \n             \nFormat          :  Audio Video Interleave               \nBitrate         :  944 kbps                            \nCodec ID        :  XviD                                 \nResolution      :  640 X 272                        \nAspect Ratio    :  2.35:1                             \nFrame Rate      :  25.000 fps                          \nQuality Frame   :  0.217\n\n\nAudio :-                                                \n            \nCodec ID        :   MP3                              \nBitrate         :   128 kbps                          \nChannel(s)      :   2                                \nSample Rate     :   48.0 KHZ   \n\n\nEncoder         :   juggs                              \nFile Size       :   698 MB                           \nDuration        :   01h30m                             \nSource          :   RUSTED(Thanks)            \nRelease Date    :  17-11-2013                         \nLanguage        :   English                            \nSubtitles       :  None                  \nSample          :   Yes\n &lt;a href=&quot;\nhttp://img585.imageshack.us/img585/8458/nklg.png&quot; rel=&quot;nofollow&quot; target=&quot;_NEW&quot;&gt;\nhttp://img585.imageshack.us/img585/8458/nklg.png&lt;/a&gt; &lt;a href=&quot;\nhttp://img833.imageshack.us/img833/1367/7qok.png&quot; rel=&quot;nofollow&quot; target=&quot;_NEW&quot;&gt;\nhttp://img833.imageshack.us/img833/1367/7qok.png&lt;/a&gt; &lt;a href=&quot;\nhttp://img845.imageshack.us/img845/2816/cdmg.png&quot; rel=&quot;nofollow&quot; target=&quot;_NEW&quot;&gt;\nhttp://img845.imageshack.us/img845/2816/cdmg.png&lt;/a&gt;\n\nMake sure it is genuine ETRG release @ extratorrent\n\nNote: if you have a problem viewing the images while clicking the links , \nplz do copy the url links and paste them to ur browser instead,or sign up to imagshack,\nor find the screenshots from my home site or other sites,or finally download a sample of the movie","torrent":{"xt":"urn:btih:f73ae0610d496418e13d7e0aa4072acdade51f87","amp;dn":"Outpost+11+%5B2012%5D+BRRip+XViD-ETRG","amp;tr":["udp%3A%2F%2Ftracker.openbittorrent.com%3A80","udp%3A%2F%2Fopen.demonii.com%3A1337","udp%3A%2F%2Ftracker.coppersurfer.tk%3A6969","udp%3A%2F%2Fexodus.desync.com%3A6969"],"infoHash":"f73ae0610d496418e13d7e0aa4072acdade51f87","infoHashBuffer":{"type":"Buffer","data":[247,58,224,97,13,73,100,24,225,61,126,10,164,7,42,205,173,229,31,135]},"announce":[],"urlList":[]}}